py2sqlite/__init__.py
py2sqlite/db_objects.py
py2sqlite/db_types/__init__.py
py2sqlite/db_types/base_types.py
py2sqlite/db_types/collections.py
py2sqlite/db_types/db_type.py
py2sqlite/db_types/utils.py
py2sqlite/py2sql.py
py2sqlite/queries.py
py2sqlite-0.7.0.dist-info/WHEEL
py2sqlite-0.7.0.dist-info/METADATA
py2sqlite-0.7.0.dist-info/RECORD
