Metadata-Version: 2.1
Name: py2sqlite
Version: 0.7.0
Summary: Python ORM for SQLite database
Author: Mykyta, Sergei
Author-email: isara.isara8@gmail.com
Requires-Python: >=3.6,<4.0
Classifier: Programming Language :: Python :: 3
Classifier: Programming Language :: Python :: 3.6
Classifier: Programming Language :: Python :: 3.7
Classifier: Programming Language :: Python :: 3.8
Classifier: Programming Language :: Python :: 3.9
Requires-Dist: jsonpickle (>=1.4.2,<2.0.0)
